scitokens/jupyter/__init__.py
scitokens/jupyter/py.typed
scitokens/jupyter/token_db.py
scitokens/jupyter/token_service.html
scitokens/jupyter/token_service.py
scitokens_jupyter-0.0.3.dist-info/LICENSE
scitokens_jupyter-0.0.3.dist-info/WHEEL
scitokens_jupyter-0.0.3.dist-info/METADATA
scitokens_jupyter-0.0.3.dist-info/RECORD
