Metadata-Version: 2.1
Name: scitokens-jupyter
Version: 0.0.3
Summary: Support for SciTokens for Project Jupyter
Home-page: https://github.com/scitokens/scitokens-jupyter
License: Apache-2.0
Author: Brian Aydemir
Author-email: baydemir@morgridge.org
Requires-Python: >=3.8,<3.9
Classifier: License :: OSI Approved :: Apache Software License
Classifier: Programming Language :: Python :: 3
Classifier: Programming Language :: Python :: 3.8
Requires-Dist: baydemir (==0.0.1)
Requires-Dist: jupyterhub (>=1.3,<1.4)
Requires-Dist: requests-oauthlib (>=1.3,<1.4)
Requires-Dist: tornado (>=6.1,<6.2)
Project-URL: Repository, https://github.com/scitokens/scitokens-jupyter
